{
  "pageNumber": 110,
  "title": "Local News & Community Events",
  "category": "NEWS",
  "severity": null,
  "content": "LOCAL NEWS\nв•ђв•ђв•ђв•ђв•ђв•ђв•ђв•ђв•ђв•ђв•ђв•ђв•ђв•ђв•ђв•ђв•ђв•ђв•ђв•ђв•ђв•ђв•ђв•ђв•ђв•ђв•ђв•ђв•ђв•ђв•ђв•ђв•ђв•ђв•ђв•ђв•ђв•ђв•ђв•ђв•ђв•ђв•ђв•ђв•ђв•ђв•ђв•ђв•ђ\n\nCommunity Events\nв”Ђв”Ђв”Ђв”Ђв”Ђв”Ђв”Ђв”Ђв”Ђв”Ђв”Ђв”Ђв”Ђв”Ђв”Ђв”Ђ\nSummer festival announced for next\nweekend at the town square.\n\nTraffic & Transport\nв”Ђв”Ђв”Ђв”Ђв”Ђв”Ђв”Ђв”Ђв”Ђв”Ђв”Ђв”Ђв”Ђв”Ђв”Ђв”Ђв”Ђв”Ђв”Ђ\nRoad works scheduled on main highway\nduring off-peak hours.\n\nLocal Politics\nв”Ђв”Ђв”Ђв”Ђв”Ђв”Ђв”Ђв”Ђв”Ђв”Ђв”Ђв”Ђв”Ђв”Ђ\nCouncil meeting to discuss new\ndevelopment proposals.\n\nPublic Services\nв”Ђв”Ђв”Ђв”Ђв”Ђв”Ђв”Ђв”Ђв”Ђв”Ђв”Ђв”Ђв”Ђв”Ђв”Ђ\nLibrary extends opening hours for\nsummer reading program.\n\nв”Ђв”Ђв”Ђв”Ђв”Ђв”Ђв”Ђв”Ђв”Ђв”Ђв”Ђв”Ђв”Ђв”Ђв”Ђв”Ђв”Ђв”Ђв”Ђв”Ђв”Ђв”Ђв”Ђв”Ђв”Ђв”Ђв”Ђв”Ђв”Ђв”Ђв”Ђв”Ђв”Ђв”Ђв”Ђв”Ђв”Ђв”Ђв”Ђв”Ђв”Ђв”Ђв”Ђв”Ђв”Ђв”Ђв”Ђв”Ђв”Ђ\nThank you for using TXT TV!\nReturn to home page: page 100\nв”Ђв”Ђв”Ђв”Ђв”Ђв”Ђв”Ђв”Ђв”Ђв”Ђв”Ђв”Ђв”Ђв”Ђв”Ђв”Ђв”Ђв”Ђв”Ђв”Ђв”Ђв”Ђв”Ђв”Ђв”Ђв”Ђв”Ђв”Ђв”Ђв”Ђв”Ђв”Ђв”Ђв”Ђв”Ђв”Ђв”Ђв”Ђв”Ђв”Ђв”Ђв”Ђв”Ђв”Ђв”Ђв”Ђв”Ђв”Ђв”Ђ\nTXT TV - Your Community News Service",
  "metadata": {
    "published": "2026-02-09T16:00:00Z"
  },
  "navigation": {
    "prev": 109,
    "next": null,
    "related": [100, 109]
  }
}
